deciphon_schema/__init__.py
deciphon_schema-0.2.0.dist-info/METADATA
deciphon_schema-0.2.0.dist-info/WHEEL
deciphon_schema-0.2.0.dist-info/RECORD
